ngpebble/__main__.py
ngpebble-0.1.1.dist-info/METADATA
ngpebble-0.1.1.dist-info/WHEEL
ngpebble-0.1.1.dist-info/entry_points.txt
ngpebble-0.1.1.dist-info/top_level.txt
ngpebble-0.1.1.dist-info/RECORD
