Metadata-Version: 2.4
Name: ngpebble
Version: 0.1.1
Summary: Ngrok-like tunnel via WebSocket
Author: Eshan Das
Requires-Python: >=3.8
Requires-Dist: websockets
Requires-Dist: requests
